cve_mcp_server/__init__.py
cve_mcp_server/__main__.py
cve_mcp_server/cve.py
cve_mcp_server/server.py
cve_mcp_server-0.5.0.dist-info/METADATA
cve_mcp_server-0.5.0.dist-info/WHEEL
cve_mcp_server-0.5.0.dist-info/entry_points.txt
cve_mcp_server-0.5.0.dist-info/licenses/LICENSE
cve_mcp_server-0.5.0.dist-info/RECORD
