Metadata-Version: 2.4
Name: cve-mcp-server
Version: 0.5.0
Summary: A Model Context Protocol server providing tools for CVE vulnerability information queries
License-File: LICENSE
Requires-Python: >=3.12
Requires-Dist: mcp>=1.7.0
Requires-Dist: requests>=2.32.3
